pydagu/__init__.py
pydagu/builder.py
pydagu/http.py
pydagu/py.typed
pydagu/models/__init__.py
pydagu/models/base.py
pydagu/models/dag.py
pydagu/models/executor.py
pydagu/models/handlers.py
pydagu/models/infrastructure.py
pydagu/models/notifications.py
pydagu/models/request.py
pydagu/models/response.py
pydagu/models/step.py
pydagu/models/types.py
pydagu-0.2.5.dist-info/METADATA
pydagu-0.2.5.dist-info/WHEEL
pydagu-0.2.5.dist-info/licenses/LICENSE
pydagu-0.2.5.dist-info/RECORD
