Metadata-Version: 2.4
Name: pydagu
Version: 0.2.5
Summary: Python client library for Dagu - A cron alternative with a Web UI
Project-URL: Homepage, https://github.com/patrickcd/pydagu
Project-URL: Documentation, https://github.com/patrickcd/pydagu#readme
Project-URL: Repository, https://github.com/patrickcd/pydagu
Project-URL: Issues, https://github.com/patrickcd/pydagu/issues
Author-email: Patrick Dobbs <patrick.dobbs@gmail.com>
License: MIT
License-File: LICENSE
Keywords: cron,dag,dagu,scheduler,workflow
Classifier: Development Status :: 3 - Alpha
Classifier: Intended Audience :: Developers
Classifier: License :: OSI Approved :: MIT License
Classifier: Programming Language :: Python :: 3
Classifier: Programming Language :: Python :: 3.13
Classifier: Programming Language :: Python :: 3.14
Classifier: Topic :: Software Development :: Libraries :: Python Modules
Classifier: Topic :: System :: Monitoring
Requires-Python: >=3.13
Requires-Dist: httpx>=0.28.1
Requires-Dist: pydantic>=2.12.3
Requires-Dist: pyyaml>=6.0.3
Provides-Extra: dev
Requires-Dist: hypothesis-jsonschema>=0.23.1; extra == 'dev'
Requires-Dist: import-linter>=2.5.2; extra == 'dev'
Requires-Dist: mypy>=1.18.2; extra == 'dev'
Requires-Dist: pre-commit>=4.3.0; extra == 'dev'
Requires-Dist: pytest-cov>=7.0.0; extra == 'dev'
Requires-Dist: pytest>=8.4.2; extra == 'dev'
Requires-Dist: ruff>=0.14.3; extra == 'dev'
Requires-Dist: schemathesis>=4.3.18; extra == 'dev'
Requires-Dist: types-pyyaml>=6.0.12.20250915; extra == 'dev'
